mb_excelexport_2csv/__init__.py
mb_excelexport_2csv/gui_model.py
mb_excelexport_2csv/main.py
mb_excelexport_2csv-0.6.0.dist-info/entry_points.txt
mb_excelexport_2csv-0.6.0.dist-info/WHEEL
mb_excelexport_2csv-0.6.0.dist-info/METADATA
mb_excelexport_2csv-0.6.0.dist-info/RECORD
