Metadata-Version: 2.1
Name: mb-excelexport-2csv
Version: 0.6.0
Summary: Parses an .xls excel file downloaded from ManageBac and converts to comma-deliminated csv. Particularly useful to convert to GSheets without having to use Excel.
Author: Adam Morris
Author-email: classroomtechtools.ctt@gmail.com
Requires-Python: >=3.6.1,<4.0.0
Classifier: Programming Language :: Python :: 3
Classifier: Programming Language :: Python :: 3.10
Classifier: Programming Language :: Python :: 3.7
Classifier: Programming Language :: Python :: 3.8
Classifier: Programming Language :: Python :: 3.9
Requires-Dist: PyQt6 (>=6.2.1,<7.0.0)
Requires-Dist: click (>=8.0.3,<9.0.0)
